vexshell/__init__.py
vexshell/__main__.py
vexshell/command_manager.py
vexshell/controller.py
vexshell/model.py
vexshell/shell.py
vexshell-0.0.1.dist-info/DESCRIPTION.rst
vexshell-0.0.1.dist-info/METADATA
vexshell-0.0.1.dist-info/RECORD
vexshell-0.0.1.dist-info/WHEEL
vexshell-0.0.1.dist-info/entry_points.txt
vexshell-0.0.1.dist-info/metadata.json
vexshell-0.0.1.dist-info/top_level.txt
