Metadata-Version: 2.0
Name: vexshell
Version: 0.0.1
Summary: shell for vexbot
Home-page: https://github.com/benhoff/vexshell
Author: Ben Hoff
Author-email: beohoff@gmail.com
License: GPL3
Platform: UNKNOWN
Classifier: Development Status :: 1 - Planning
Classifier: Intended Audience :: Developers
Classifier: License :: OSI Approved :: GNU General Public License v3 (GPLv3)
Classifier: Programming Language :: Python :: 3
Classifier: Programming Language :: Python :: 3.5
Classifier: Operating System :: OS Independent
Requires-Dist: pyzmq
Requires-Dist: vexbot
Requires-Dist: vexmessage
